py4cli/minimal.py
py4cli-0.0.4.dist-info/LICENSE.txt
py4cli-0.0.4.dist-info/METADATA
py4cli-0.0.4.dist-info/WHEEL
py4cli-0.0.4.dist-info/top_level.txt
py4cli-0.0.4.dist-info/RECORD
