Metadata-Version: 2.1
Name: py4cli
Version: 0.0.4
Summary: python for command line interface development
Home-page: https://github.com/Palani-SN/py4cli
Author: Palani-SN
Author-email: psn396@gmail.com
Classifier: Programming Language :: Python :: 3
Classifier: Programming Language :: Python :: 3.7
Classifier: License :: OSI Approved :: GNU General Public License v3 or later (GPLv3+)
Classifier: Operating System :: OS Independent
License-File: LICENSE.txt
Requires-Dist: blessings (~=1.7)
Provides-Extra: dev
Requires-Dist: pytest (>=3.7) ; extra == 'dev'
Requires-Dist: check-manifest ; extra == 'dev'
Requires-Dist: twine ; extra == 'dev'
